pelyx/__init__.py
pelyx/__main__.py
pelyx/cli.py
pelyx/editor.py
pelyx-0.0.3.dist-info/licenses/license
pelyx-0.0.3.dist-info/METADATA
pelyx-0.0.3.dist-info/WHEEL
pelyx-0.0.3.dist-info/entry_points.txt
pelyx-0.0.3.dist-info/top_level.txt
pelyx-0.0.3.dist-info/RECORD
