Metadata-Version: 2.4
Name: pelyx
Version: 0.0.3
Summary: Pelyx plans to be a toy terminal editor
Author-email: Obvodny <obvodny@yeah.net>
Maintainer-email: Obvodny <obvodny@yeah.net>
License-Expression: MulanPSL-2.0
Keywords: editor
Classifier: Development Status :: 1 - Planning
Classifier: Environment :: Console
Classifier: Operating System :: MacOS
Classifier: Operating System :: Microsoft :: Windows :: Windows 10
Classifier: Operating System :: Microsoft :: Windows :: Windows 11
Classifier: Operating System :: POSIX :: Linux
Classifier: Programming Language :: Python :: 3
Classifier: Topic :: Text Editors
Requires-Python: >=3.9
License-File: license
Requires-Dist: textual
Requires-Dist: wcwidth
Dynamic: license-file
